gnfetcher/__init__.py
gnfetcher/gnfetcher.py
gnfetcher/userexception.py
gnfetcher/utils.py
gnfetcher/scripts/__init__.py
gnfetcher/scripts/gnews.py
gnfetcher-1.0.1.data/scripts/gnews-gui
gnfetcher-1.0.1.dist-info/LICENSE.txt
gnfetcher-1.0.1.dist-info/METADATA
gnfetcher-1.0.1.dist-info/WHEEL
gnfetcher-1.0.1.dist-info/entry_points.txt
gnfetcher-1.0.1.dist-info/top_level.txt
gnfetcher-1.0.1.dist-info/RECORD
