Metadata-Version: 2.1
Name: gnfetcher
Version: 1.0.1
Summary: Python client for Google News feed.
Home-page: http://github.com/aadu999/gnfetcher
Author: Adarsh Raveendra
Author-email: hello@adarsh.online
License: MIT
Keywords: google news feed python tool
Platform: UNKNOWN
Classifier: Development Status :: 4 - Beta
Classifier: License :: OSI Approved :: MIT License
Classifier: Programming Language :: Python
Classifier: Programming Language :: Python :: 2
Classifier: Programming Language :: Python :: 2.6
Classifier: Programming Language :: Python :: 2.7
Classifier: Programming Language :: Python :: 3
Classifier: Programming Language :: Python :: 3.3
Classifier: Programming Language :: Python :: 3.4
Classifier: Programming Language :: Python :: 3.5
Classifier: Topic :: Internet
Requires-Dist: requests
Requires-Dist: bs4
Requires-Dist: html5lib
Requires-Dist: Click
